hs_rpc/__init__.py
hs_rpc/decorates.py
hs_rpc/exceptions.py
hs_rpc/request.py
hs_rpc/rpc.py
hs_rpc/server.py
hs_rpc/proto/__init__.py
hs_rpc/proto/rpc_data_pb2.py
hs_rpc/proto/rpc_data_pb2_grpc.py
hs_rpc-0.1.7.dist-info/LICENSE
hs_rpc-0.1.7.dist-info/METADATA
hs_rpc-0.1.7.dist-info/WHEEL
hs_rpc-0.1.7.dist-info/top_level.txt
hs_rpc-0.1.7.dist-info/RECORD
