Metadata-Version: 2.1
Name: hs-rpc
Version: 0.1.7
Summary: rpc服务打包
Home-page: UNKNOWN
Author: huansi_mes_team
Author-email: 751995207@qq.com
License: UNKNOWN
Platform: UNKNOWN
Classifier: Programming Language :: Python :: 3
Classifier: License :: OSI Approved :: MIT License
Classifier: Operating System :: OS Independent
Requires-Dist: Click
Requires-Dist: Flask
Requires-Dist: google
Requires-Dist: grpcio
Requires-Dist: protobuf
Requires-Dist: soupsieve
Requires-Dist: six
Requires-Dist: retrying
